sixriver_ros_utils/__init__.py
sixriver_ros_utils/state.py
sixriver_ros_utils/houph/__init__.py
sixriver_ros_utils/houph/houph.py
sixriver_ros_utils/plotting/PlotOdometryFromBag.py
sixriver_ros_utils/plotting/__init__.py
sixriver_ros_utils/plotting/ce_test_analysis.py
sixriver_ros_utils/plotting/cm_expansion.py
sixriver_ros_utils/plotting/plot.py
sixriver_ros_utils/plotting/plot_scored_sampling_planner_costs.py
sixriver_ros_utils/plotting/plotters/__init__.py
sixriver_ros_utils/plotting/plotters/ce_optitrack_test_plotter.py
sixriver_ros_utils/plotting/plotters/ce_test_plotter.py
sixriver_ros_utils/plotting/plotters/docking_plotter.py
sixriver_ros_utils/plotting/plotters/hard_stop_test_plotter.py
sixriver_ros_utils/plotting/plotters/plot_utils.py
sixriver_ros_utils/plotting/plotters/tf_diff.py
sixriver_ros_utils/plotting/plotters/velocity_plotter.py
sixriver_ros_utils/rosbag_tools/WriteCSVFromBag.py
sixriver_ros_utils/rosbag_tools/__init__.py
sixriver_ros_utils/rosbag_tools/bag2csv.py
sixriver_ros_utils/rosbag_tools/bagSize.py
sixriver_ros_utils/rosbag_tools/map.py
sixriver_ros_utils/rosbag_tools/noAccelnoMapFrame.py
sixriver_ros_utils/rosbag_tools/rosbag_merge.py
sixriver_ros_utils-0.0.6.dist-info/LICENSE
sixriver_ros_utils-0.0.6.dist-info/METADATA
sixriver_ros_utils-0.0.6.dist-info/WHEEL
sixriver_ros_utils-0.0.6.dist-info/top_level.txt
sixriver_ros_utils-0.0.6.dist-info/RECORD
