Metadata-Version: 2.1
Name: sixriver-ros-utils
Version: 0.0.6
Summary: Ros util for python
Home-page: https://github.com/6RiverSystems/mfp_tools
Author: sixriver
Author-email: dniktopoulos@6river.com
License: UNKNOWN
Platform: UNKNOWN
Requires-Python: >=2.7
